font_analyzer/__init__.py
font_analyzer/main.py
font_analyzer/config/__init__.py
font_analyzer/config/settings.py
font_analyzer/core/__init__.py
font_analyzer/core/analyzer.py
font_analyzer/core/metadata.py
font_analyzer/core/whitelist.py
font_analyzer/utils/__init__.py
font_analyzer/utils/formatter.py
font_analyzer/utils/logger.py
font_analyzer/utils/web_scraper.py
font_analyzer-0.0.6.dist-info/licenses/LICENSE
font_analyzer-0.0.6.dist-info/METADATA
font_analyzer-0.0.6.dist-info/WHEEL
font_analyzer-0.0.6.dist-info/entry_points.txt
font_analyzer-0.0.6.dist-info/top_level.txt
font_analyzer-0.0.6.dist-info/RECORD
