Metadata-Version: 2.4
Name: font-analyzer
Version: 0.0.6
Summary: A tool for detecting and analyzing font metadata from websites and files
Author-email: Aykut Cantürk <canturk.aykut@gmail.com>
License-Expression: MIT
Project-URL: Homepage, https://github.com/aykut-canturk/font-analyzer
Project-URL: Repository, https://github.com/aykut-canturk/font-analyzer
Project-URL: Issues, https://github.com/aykut-canturk/font-analyzer/issues
Keywords: font,metadata,analysis,web-scraping,typography
Classifier: Development Status :: 4 - Beta
Classifier: Intended Audience :: Developers
Classifier: Programming Language :: Python :: 3
Classifier: Programming Language :: Python :: 3.8
Classifier: Programming Language :: Python :: 3.9
Classifier: Programming Language :: Python :: 3.10
Classifier: Programming Language :: Python :: 3.11
Classifier: Programming Language :: Python :: 3.12
Classifier: Topic :: Text Processing :: Fonts
Classifier: Topic :: Software Development :: Libraries :: Python Modules
Requires-Python: >=3.8.1
License-File: LICENSE
Requires-Dist: requests
Requires-Dist: beautifulsoup4
Requires-Dist: fonttools
Requires-Dist: brotli
Requires-Dist: colorama
Requires-Dist: pyyaml
Requires-Dist: python-dotenv
Dynamic: license-file
